Metadata-Version: 2.1
Name: pyegrep
Version: 1.0.7
Summary: A tool for grep
Home-page: https://github.com/kanz84/pyegrep
Download-URL: https://github.com/kanz84/pyegrep/archive/refs/tags/v1.0.5.tar.gz
Author: kanz84
Author-email: kanz1384@gmail.com
License: MIT
Keywords: grep,egrep
Classifier: Intended Audience :: Developers
Classifier: Topic :: Software Development :: Build Tools
Classifier: License :: OSI Approved :: MIT License
Classifier: Programming Language :: Python :: 3
Classifier: Programming Language :: Python :: 3.4
Classifier: Programming Language :: Python :: 3.5
Classifier: Programming Language :: Python :: 3.6
Classifier: Programming Language :: Python :: 3.7
Classifier: Programming Language :: Python :: 3.8
Classifier: Programming Language :: Python :: 3.9
License-File: LICENSE
